{"openapi":"3.1.0","info":{"title":"API de Gestión Empresarial","version":"1.0"},"paths":{"/auth/register":{"post":{"tags":["Autenticación"],"summary":"Register","operationId":"register_auth_register_post","requestBody":{"content":{"application/json":{"schema":{"$ref":"#/components/schemas/UsuarioRegistro"}}},"required":true},"responses":{"200":{"description":"Successful Response","content":{"application/json":{"schema":{}}}},"422":{"description":"Validation Error","content":{"application/json":{"schema":{"$ref":"#/components/schemas/HTTPValidationError"}}}}}}},"/auth/login":{"post":{"tags":["Autenticación"],"summary":"Login","operationId":"login_auth_login_post","requestBody":{"content":{"application/json":{"schema":{"$ref":"#/components/schemas/UsuarioLogin"}}},"required":true},"responses":{"200":{"description":"Successful Response","content":{"application/json":{"schema":{}}}},"422":{"description":"Validation Error","content":{"application/json":{"schema":{"$ref":"#/components/schemas/HTTPValidationError"}}}}}}},"/clientes/":{"post":{"tags":["Clientes"],"summary":"Crear Cliente","operationId":"crear_cliente_clientes__post","requestBody":{"required":true,"content":{"application/json":{"schema":{"$ref":"#/components/schemas/ClienteSchema"}}}},"responses":{"200":{"description":"Successful Response","content":{"application/json":{"schema":{"type":"object","title":"Response Crear Cliente Clientes  Post"}}}},"422":{"description":"Validation Error","content":{"application/json":{"schema":{"$ref":"#/components/schemas/HTTPValidationError"}}}}}},"get":{"tags":["Clientes"],"summary":"Obtener Clientes","operationId":"obtener_clientes_clientes__get","parameters":[{"name":"search","in":"query","required":false,"schema":{"type":"string","description":"Buscar cliente por nombre","title":"Search"},"description":"Buscar cliente por nombre"}],"responses":{"200":{"description":"Successful Response","content":{"application/json":{"schema":{"type":"array","items":{"$ref":"#/components/schemas/ClienteSchema"},"title":"Response Obtener Clientes Clientes  Get"}}}},"422":{"description":"Validation Error","content":{"application/json":{"schema":{"$ref":"#/components/schemas/HTTPValidationError"}}}}}}},"/clientes/{cliente_id}":{"put":{"tags":["Clientes"],"summary":"Actualizar Cliente","operationId":"actualizar_cliente_clientes__cliente_id__put","parameters":[{"name":"cliente_id","in":"path","required":true,"schema":{"type":"integer","title":"Cliente Id"}}],"requestBody":{"required":true,"content":{"application/json":{"schema":{"$ref":"#/components/schemas/ClienteSchema"}}}},"responses":{"200":{"description":"Successful Response","content":{"application/json":{"schema":{"$ref":"#/components/schemas/ClienteSchema"}}}},"422":{"description":"Validation Error","content":{"application/json":{"schema":{"$ref":"#/components/schemas/HTTPValidationError"}}}}}},"delete":{"tags":["Clientes"],"summary":"Eliminar Cliente","operationId":"eliminar_cliente_clientes__cliente_id__delete","parameters":[{"name":"cliente_id","in":"path","required":true,"schema":{"type":"integer","title":"Cliente Id"}}],"responses":{"200":{"description":"Successful Response","content":{"application/json":{"schema":{}}}},"422":{"description":"Validation Error","content":{"application/json":{"schema":{"$ref":"#/components/schemas/HTTPValidationError"}}}}}}},"/productos/":{"get":{"tags":["Productos"],"summary":"Obtener Productos","operationId":"obtener_productos_productos__get","responses":{"200":{"description":"Successful Response","content":{"application/json":{"schema":{"items":{"$ref":"#/components/schemas/ProductoResponseSchema"},"type":"array","title":"Response Obtener Productos Productos  Get"}}}}}}},"/ventas/":{"post":{"tags":["Órdenes de Venta"],"summary":"Crear Pedido","operationId":"crear_pedido_ventas__post","requestBody":{"content":{"application/json":{"schema":{"$ref":"#/components/schemas/PedidoCreateSchema"}}},"required":true},"responses":{"200":{"description":"Successful Response","content":{"application/json":{"schema":{"$ref":"#/components/schemas/PedidoResponseSchema"}}}},"422":{"description":"Validation Error","content":{"application/json":{"schema":{"$ref":"#/components/schemas/HTTPValidationError"}}}}}}},"/tesoreria/":{"post":{"tags":["Tesorería"],"summary":"Registrar Transaccion","operationId":"registrar_transaccion_tesoreria__post","requestBody":{"content":{"application/json":{"schema":{"$ref":"#/components/schemas/TransaccionSchema"}}},"required":true},"responses":{"200":{"description":"Successful Response","content":{"application/json":{"schema":{"$ref":"#/components/schemas/TransaccionResponseSchema"}}}},"422":{"description":"Validation Error","content":{"application/json":{"schema":{"$ref":"#/components/schemas/HTTPValidationError"}}}}}}},"/cuentas-wallet/":{"get":{"tags":["Cuentas Wallet"],"summary":"Obtener Cuentas Wallet","operationId":"obtener_cuentas_wallet_cuentas_wallet__get","responses":{"200":{"description":"Successful Response","content":{"application/json":{"schema":{"items":{"$ref":"#/components/schemas/CuentaWalletResponseSchema"},"type":"array","title":"Response Obtener Cuentas Wallet Cuentas Wallet  Get"}}}}}},"post":{"tags":["Cuentas Wallet"],"summary":"Crear Cuenta Wallet","operationId":"crear_cuenta_wallet_cuentas_wallet__post","requestBody":{"content":{"application/json":{"schema":{"$ref":"#/components/schemas/CuentaWalletSchema"}}},"required":true},"responses":{"200":{"description":"Successful Response","content":{"application/json":{"schema":{"$ref":"#/components/schemas/CuentaWalletResponseSchema"}}}},"422":{"description":"Validation Error","content":{"application/json":{"schema":{"$ref":"#/components/schemas/HTTPValidationError"}}}}}}},"/chats/":{"get":{"tags":["Chats"],"summary":"Obtener Mensajes Chat","operationId":"obtener_mensajes_chat_chats__get","responses":{"200":{"description":"Successful Response","content":{"application/json":{"schema":{"items":{"$ref":"#/components/schemas/ChatResponseSchema"},"type":"array","title":"Response Obtener Mensajes Chat Chats  Get"}}}}}},"post":{"tags":["Chats"],"summary":"Crear Mensaje Chat","operationId":"crear_mensaje_chat_chats__post","requestBody":{"content":{"application/json":{"schema":{"$ref":"#/components/schemas/ChatSchema"}}},"required":true},"responses":{"200":{"description":"Successful Response","content":{"application/json":{"schema":{"$ref":"#/components/schemas/ChatResponseSchema"}}}},"422":{"description":"Validation Error","content":{"application/json":{"schema":{"$ref":"#/components/schemas/HTTPValidationError"}}}}}}},"/catalogos/tipos-documento":{"get":{"tags":["Catálogos"],"summary":"Obtener Tipos Documento","operationId":"obtener_tipos_documento_catalogos_tipos_documento_get","responses":{"200":{"description":"Successful Response","content":{"application/json":{"schema":{}}}}}}},"/catalogos/regimenes-tributarios":{"get":{"tags":["Catálogos"],"summary":"Obtener Regimenes Tributarios","operationId":"obtener_regimenes_tributarios_catalogos_regimenes_tributarios_get","responses":{"200":{"description":"Successful Response","content":{"application/json":{"schema":{}}}}}}},"/catalogos/tipos-persona":{"get":{"tags":["Catálogos"],"summary":"Obtener Tipos Persona","operationId":"obtener_tipos_persona_catalogos_tipos_persona_get","responses":{"200":{"description":"Successful Response","content":{"application/json":{"schema":{}}}}}}},"/catalogos/monedas":{"get":{"tags":["Catálogos"],"summary":"Obtener Monedas","operationId":"obtener_monedas_catalogos_monedas_get","responses":{"200":{"description":"Successful Response","content":{"application/json":{"schema":{}}}}}}},"/catalogos/tarifas-precios":{"get":{"tags":["Catálogos"],"summary":"Obtener Tarifas Precios","operationId":"obtener_tarifas_precios_catalogos_tarifas_precios_get","responses":{"200":{"description":"Successful Response","content":{"application/json":{"schema":{}}}}}}},"/catalogos/actividades-economicas":{"get":{"tags":["Catálogos"],"summary":"Obtener Actividades Economicas","operationId":"obtener_actividades_economicas_catalogos_actividades_economicas_get","responses":{"200":{"description":"Successful Response","content":{"application/json":{"schema":{}}}}}}},"/catalogos/formas-pago":{"get":{"tags":["Catálogos"],"summary":"Obtener Formas Pago","operationId":"obtener_formas_pago_catalogos_formas_pago_get","responses":{"200":{"description":"Successful Response","content":{"application/json":{"schema":{}}}}}}},"/catalogos/retenciones":{"get":{"tags":["Catálogos"],"summary":"Obtener Retenciones","operationId":"obtener_retenciones_catalogos_retenciones_get","responses":{"200":{"description":"Successful Response","content":{"application/json":{"schema":{}}}}}}},"/catalogos/tipos-marketing":{"get":{"tags":["Catálogos"],"summary":"Obtener Tipos Marketing","operationId":"obtener_tipos_marketing_catalogos_tipos_marketing_get","responses":{"200":{"description":"Successful Response","content":{"application/json":{"schema":{}}}}}}},"/catalogos/sucursales":{"get":{"tags":["Catálogos"],"summary":"Obtener Sucursales","operationId":"obtener_sucursales_catalogos_sucursales_get","responses":{"200":{"description":"Successful Response","content":{"application/json":{"schema":{}}}}}}},"/catalogos/rutas-logisticas":{"get":{"tags":["Catálogos"],"summary":"Obtener Rutas Logisticas","operationId":"obtener_rutas_logisticas_catalogos_rutas_logisticas_get","responses":{"200":{"description":"Successful Response","content":{"application/json":{"schema":{}}}}}}},"/catalogos/vendedores":{"get":{"tags":["Catálogos"],"summary":"Obtener Vendedores","operationId":"obtener_vendedores_catalogos_vendedores_get","responses":{"200":{"description":"Successful Response","content":{"application/json":{"schema":{}}}}}}},"/":{"get":{"summary":"Home","operationId":"home__get","responses":{"200":{"description":"Successful Response","content":{"application/json":{"schema":{}}}}}}}},"components":{"schemas":{"ChatResponseSchema":{"properties":{"usuario_id":{"type":"integer","title":"Usuario Id"},"mensaje":{"type":"string","title":"Mensaje"},"fecha":{"type":"string","format":"date-time","title":"Fecha","default":"2025-02-23T14:28:03.549306"},"id":{"type":"integer","title":"Id"}},"type":"object","required":["usuario_id","mensaje","id"],"title":"ChatResponseSchema"},"ChatSchema":{"properties":{"usuario_id":{"type":"integer","title":"Usuario Id"},"mensaje":{"type":"string","title":"Mensaje"},"fecha":{"type":"string","format":"date-time","title":"Fecha","default":"2025-02-23T14:28:03.549306"}},"type":"object","required":["usuario_id","mensaje"],"title":"ChatSchema"},"ClienteSchema":{"properties":{"id":{"anyOf":[{"type":"integer"},{"type":"null"}],"title":"Id"},"tipo_documento_id":{"type":"integer","title":"Tipo Documento Id"},"numero_documento":{"type":"string","maxLength":20,"minLength":3,"title":"Numero Documento"},"nombre_razon_social":{"type":"string","minLength":3,"title":"Nombre Razon Social"},"email":{"type":"string","format":"email","title":"Email"},"departamento_id":{"type":"integer","title":"Departamento Id"},"ciudad_id":{"type":"integer","title":"Ciudad Id"},"direccion":{"type":"string","minLength":5,"title":"Direccion"},"telefono1":{"anyOf":[{"type":"string"},{"type":"null"}],"title":"Telefono1"},"telefono2":{"anyOf":[{"type":"string"},{"type":"null"}],"title":"Telefono2"},"celular":{"anyOf":[{"type":"string"},{"type":"null"}],"title":"Celular"},"whatsapp":{"anyOf":[{"type":"string"},{"type":"null"}],"title":"Whatsapp"},"tipos_persona_id":{"type":"integer","title":"Tipos Persona Id","default":1},"regimen_tributario_id":{"type":"integer","title":"Regimen Tributario Id","default":5},"moneda_principal_id":{"type":"integer","title":"Moneda Principal Id","default":1},"tarifa_precios_id":{"type":"integer","title":"Tarifa Precios Id","default":1},"forma_pago_id":{"type":"integer","title":"Forma Pago Id","default":1},"permitir_venta":{"type":"boolean","title":"Permitir Venta","default":true},"descuento":{"anyOf":[{"type":"number"},{"type":"null"}],"title":"Descuento","default":0.0},"cupo_credito":{"anyOf":[{"type":"number"},{"type":"null"}],"title":"Cupo Credito","default":0.0},"sucursal_id":{"type":"integer","title":"Sucursal Id","default":1},"vendedor_id":{"type":"integer","title":"Vendedor Id","default":1},"pagina_web":{"anyOf":[{"type":"string"},{"type":"null"}],"title":"Pagina Web"},"actividad_economica_id":{"anyOf":[{"type":"integer"},{"type":"null"}],"title":"Actividad Economica Id"},"retencion_id":{"anyOf":[{"type":"integer"},{"type":"null"}],"title":"Retencion Id"},"tipo_marketing_id":{"anyOf":[{"type":"integer"},{"type":"null"}],"title":"Tipo Marketing Id"},"ruta_logistica_id":{"anyOf":[{"type":"integer"},{"type":"null"}],"title":"Ruta Logistica Id"},"observacion":{"anyOf":[{"type":"string"},{"type":"null"}],"title":"Observacion"}},"type":"object","required":["tipo_documento_id","numero_documento","nombre_razon_social","email","departamento_id","ciudad_id","direccion"],"title":"ClienteSchema"},"CuentaWalletResponseSchema":{"properties":{"usuario_id":{"type":"integer","title":"Usuario Id"},"saldo":{"type":"string","title":"Saldo","default":0.0},"id":{"type":"integer","title":"Id"}},"type":"object","required":["usuario_id","id"],"title":"CuentaWalletResponseSchema"},"CuentaWalletSchema":{"properties":{"usuario_id":{"type":"integer","title":"Usuario Id"},"saldo":{"anyOf":[{"type":"number"},{"type":"string"}],"title":"Saldo","default":0.0}},"type":"object","required":["usuario_id"],"title":"CuentaWalletSchema"},"HTTPValidationError":{"properties":{"detail":{"items":{"$ref":"#/components/schemas/ValidationError"},"type":"array","title":"Detail"}},"type":"object","title":"HTTPValidationError"},"PedidoCreateSchema":{"properties":{"cliente_id":{"type":"integer","title":"Cliente Id"},"productos":{"items":{"type":"integer"},"type":"array","title":"Productos"},"estado":{"anyOf":[{"type":"string"},{"type":"null"}],"title":"Estado","default":"pendiente"}},"type":"object","required":["cliente_id","productos"],"title":"PedidoCreateSchema"},"PedidoResponseSchema":{"properties":{"cliente_id":{"type":"integer","title":"Cliente Id"},"productos":{"items":{"type":"integer"},"type":"array","title":"Productos"},"estado":{"anyOf":[{"type":"string"},{"type":"null"}],"title":"Estado","default":"pendiente"},"id":{"type":"integer","title":"Id"},"fecha":{"type":"string","format":"date-time","title":"Fecha"}},"type":"object","required":["cliente_id","productos","id","fecha"],"title":"PedidoResponseSchema"},"ProductoResponseSchema":{"properties":{"nombre":{"type":"string","title":"Nombre"},"codigo_barras":{"anyOf":[{"type":"string"},{"type":"null"}],"title":"Codigo Barras"},"categoria_id":{"type":"integer","title":"Categoria Id"},"precio":{"type":"string","title":"Precio"},"stock":{"type":"integer","title":"Stock"},"unidad_medida":{"type":"string","title":"Unidad Medida"},"datos_adicionales":{"anyOf":[{"type":"object"},{"type":"null"}],"title":"Datos Adicionales"},"id":{"type":"integer","title":"Id"}},"type":"object","required":["nombre","categoria_id","precio","stock","unidad_medida","id"],"title":"ProductoResponseSchema"},"TransaccionResponseSchema":{"properties":{"tipo":{"type":"string","title":"Tipo"},"monto":{"type":"number","title":"Monto"},"descripcion":{"anyOf":[{"type":"string"},{"type":"null"}],"title":"Descripcion"},"id":{"type":"integer","title":"Id"},"fecha":{"type":"string","format":"date-time","title":"Fecha"}},"type":"object","required":["tipo","monto","id","fecha"],"title":"TransaccionResponseSchema"},"TransaccionSchema":{"properties":{"tipo":{"type":"string","title":"Tipo"},"monto":{"type":"number","title":"Monto"},"descripcion":{"anyOf":[{"type":"string"},{"type":"null"}],"title":"Descripcion"}},"type":"object","required":["tipo","monto"],"title":"TransaccionSchema"},"UsuarioLogin":{"properties":{"username":{"type":"string","format":"email","title":"Username"},"password":{"type":"string","title":"Password"}},"type":"object","required":["username","password"],"title":"UsuarioLogin"},"UsuarioRegistro":{"properties":{"nombre":{"type":"string","title":"Nombre"},"email":{"type":"string","format":"email","title":"Email"},"password":{"type":"string","title":"Password"},"rol":{"type":"string","title":"Rol"},"es_admin":{"type":"boolean","title":"Es Admin","default":false}},"type":"object","required":["nombre","email","password","rol"],"title":"UsuarioRegistro"},"ValidationError":{"properties":{"loc":{"items":{"anyOf":[{"type":"string"},{"type":"integer"}]},"type":"array","title":"Location"},"msg":{"type":"string","title":"Message"},"type":{"type":"string","title":"Error Type"}},"type":"object","required":["loc","msg","type"],"title":"ValidationError"}}}}